{
	"_meta": {
		"sources": [
			{
				"json": "CreatureCohortsTheGenie",
				"abbreviation": "CC:G",
				"full": "Creature Cohorts: The Genie",
				"authors": [
					"u/Mister_Thr33"
				],
				"convertedBy": [
					"Fireyfox"
				],
				"version": "1.0.0",
				"url": "https://www.gmbinder.com/share/-N78C0W6fYwrnJIFnwI8",
				"targetSchema": "1.0.0",
				"color": "2be0a7"
			}
		],
		"dateAdded": 1667870352,
		"dateLastModified": 1726351540,
		"_dateLastModifiedHash": "e750ed177e"
	},
	"class": [
		{
			"name": "Warrior-Sage",
			"source": "CreatureCohortsTheGenie",
			"page": 2,
			"hd": {
				"number": 1,
				"faces": 10
			},
			"proficiency": [
				"con",
				"cha"
			],
			"spellcastingAbility": "cha",
			"casterProgression": "1/2",
			"classSpells": [
				"Burning Hands",
				"Color Spray",
				"Comprehend Languages",
				"Create or Destroy Water",
				"Detect Magic",
				"Disguise Self",
				"Expeditious Retreat",
				"Feather Fall",
				"Fog Cloud",
				"Identify",
				"Illusory Script",
				"Silent Image",
				"Sleep",
				"Thunderwave",
				"Unseen Servant",
				"Alter Self",
				"Arcane Lock",
				"Blur",
				"Continual Flame",
				"Enlarge/Reduce",
				"Heat Metal",
				"Invisibility",
				"Knock",
				"Levitate",
				"Mirror Image",
				"Misty Step",
				"Nystul's Magic Aura",
				"Shatter",
				"Blink",
				"Counterspell",
				"Create Food and Water",
				"Dispel Magic",
				"Fly",
				"Hypnotic Pattern",
				"Leomund's Tiny Hut",
				"Lightning Bolt",
				"Magic Circle",
				"Protection from Energy",
				"Sending",
				"Slow",
				"Tongues",
				"Banishment",
				"Conjure Minor Elementals",
				"Dimension Door",
				"Fabricate",
				"Mordenkainen's Private Sanctum",
				"Otiluke's Resilient Sphere",
				"Polymorph",
				"Conjure Elemental",
				"Contact Other Plane",
				"Creation",
				"Legend Lore",
				"Passwall",
				"Planar Binding",
				"Teleportation Circle"
			],
			"startingProficiencies": {
				"armor": [
					"light",
					"medium",
					"heavy",
					"shield"
				],
				"weapons": [
					"simple",
					"martial"
				],
				"skills": [
					{
						"choose": {
							"from": [
								"athletics",
								"arcana",
								"deception",
								"history",
								"insight",
								"intimidation",
								"perception",
								"persuasion"
							],
							"count": 2
						}
					}
				]
			},
			"startingEquipment": {
				"additionalFromBackground": true,
				"default": [
					"(a) a {@item maul|phb|maul} or (b) any martial melee weapon",
					"(a) four {@item javelin|phb|javelins} or (b) any simple weapon",
					"(a) an {@item explorer's pack|phb} and 25 gp"
				]
			},
			"classTableGroups": [
				{
					"colLabels": [
						"{@filter 1st|spells|level=1|class=Warrior-Sage (CC:G)}",
						"{@filter 2nd|spells|level=2|class=Warrior-Sage (CC:G)}",
						"{@filter 3rd|spells|level=3|class=Warrior-Sage (CC:G)}",
						"{@filter 4th|spells|level=4|class=Warrior-Sage (CC:G)}",
						"{@filter 5th|spells|level=5|class=Warrior-Sage (CC:G)}"
					],
					"rows": [
						[
							0,
							0,
							0,
							0,
							0
						],
						[
							2,
							0,
							0,
							0,
							0
						],
						[
							3,
							0,
							0,
							0,
							0
						],
						[
							3,
							0,
							0,
							0,
							0
						],
						[
							4,
							2,
							0,
							0,
							0
						],
						[
							4,
							2,
							0,
							0,
							0
						],
						[
							4,
							3,
							0,
							0,
							0
						],
						[
							4,
							3,
							0,
							0,
							0
						],
						[
							4,
							3,
							2,
							0,
							0
						],
						[
							4,
							3,
							2,
							0,
							0
						],
						[
							4,
							3,
							3,
							0,
							0
						],
						[
							4,
							3,
							3,
							0,
							0
						],
						[
							4,
							3,
							3,
							1,
							0
						],
						[
							4,
							3,
							3,
							1,
							0
						],
						[
							4,
							3,
							3,
							2,
							0
						],
						[
							4,
							3,
							3,
							2,
							0
						],
						[
							4,
							3,
							3,
							3,
							1
						],
						[
							4,
							3,
							3,
							3,
							1
						],
						[
							4,
							3,
							3,
							3,
							2
						],
						[
							4,
							3,
							3,
							3,
							2
						]
					]
				}
			],
			"classFeatures": [
				"Grant Desire|Warrior-Sage|CreatureCohortsTheGenie|1",
				"Natural Armor|Warrior-Sage|CreatureCohortsTheGenie|1",
				"Resilience|Warrior-Sage|CreatureCohortsTheGenie|1",
				"Lore-Bearer|Warrior-Sage|CreatureCohortsTheGenie|2",
				"Planar weapon|Warrior-Sage|CreatureCohortsTheGenie|2",
				"Spellcasting|Warrior-Sage|CreatureCohortsTheGenie|2",
				{
					"classFeature": "Aspect|Warrior-Sage|CreatureCohortsTheGenie|3",
					"gainSubclassFeature": true
				},
				"Ageless Technique|Warrior-Sage|CreatureCohortsTheGenie|3",
				"Ability Score Improvement|Warrior-Sage|CreatureCohortsTheGenie|4",
				"Extra Attack|Warrior-Sage|CreatureCohortsTheGenie|5",
				"Might of the Elements|Warrior-Sage|CreatureCohortsTheGenie|6",
				{
					"classFeature": "Aspect Feature|Warrior-Sage|CreatureCohortsTheGenie|7",
					"gainSubclassFeature": true
				},
				"Resilience (2)|Warrior-Sage|CreatureCohortsTheGenie|7",
				"Ability Score Improvement|Warrior-Sage|CreatureCohortsTheGenie|8",
				{
					"classFeature": "Aspect Feature|Warrior-Sage|CreatureCohortsTheGenie|10",
					"gainSubclassFeature": true
				},
				"Planar Conduit|Warrior-Sage|CreatureCohortsTheGenie|11",
				"Ability Score Improvement|Warrior-Sage|CreatureCohortsTheGenie|12",
				"Plane Shift|Warrior-Sage|CreatureCohortsTheGenie|14",
				{
					"classFeature": "Aspect Feature|Warrior-Sage|CreatureCohortsTheGenie|15",
					"gainSubclassFeature": true
				},
				"Ability Score Improvement|Warrior-Sage|CreatureCohortsTheGenie|16",
				"Resilience (3)|Warrior-Sage|CreatureCohortsTheGenie|18",
				"Ability Score Improvement|Warrior-Sage|CreatureCohortsTheGenie|19",
				"Wishmonger|Warrior-Sage|CreatureCohortsTheGenie|20"
			],
			"subclassTitle": "Aspect"
		}
	],
	"subclass": [
		{
			"name": "Dao",
			"shortName": "Dao",
			"source": "CreatureCohortsTheGenie",
			"className": "Warrior-Sage",
			"classSource": "CreatureCohortsTheGenie",
			"page": 8,
			"additionalSpells": [
				{
					"known": {
						"3": [
							"compelled duel",
							"shield"
						],
						"5": [
							"melf's acid arrow",
							"ray of enfeeblement"
						],
						"9": [
							"magic circle",
							"meld into stone"
						],
						"13": [
							"banishment",
							"stone shape"
						],
						"17": [
							"hold monster",
							"planar binding"
						]
					}
				}
			],
			"subclassFeatures": [
				"Dao|Warrior-Sage|CreatureCohortsTheGenie|Dao|CreatureCohortsTheGenie|3",
				"Appeal to Power|Warrior-Sage|CreatureCohortsTheGenie|Dao|CreatureCohortsTheGenie|7",
				"Terran Heritage|Warrior-Sage|CreatureCohortsTheGenie|Dao|CreatureCohortsTheGenie|10",
				"From Beneath the Earth|Warrior-Sage|CreatureCohortsTheGenie|Dao|CreatureCohortsTheGenie|15"
			]
		},
		{
			"name": "Djinni",
			"shortName": "Djinni",
			"source": "CreatureCohortsTheGenie",
			"className": "Warrior-Sage",
			"classSource": "CreatureCohortsTheGenie",
			"page": 9,
			"additionalSpells": [
				{
					"known": {
						"3": [
							"magic missile",
							"shield"
						],
						"5": [
							"misty step",
							"insibility"
						],
						"9": [
							"blink",
							"lightning arrow"
						],
						"13": [
							"dimension door",
							"freedom of movement"
						],
						"17": [
							"animate objects",
							"creation"
						]
					}
				}
			],
			"subclassFeatures": [
				"Djinni|Warrior-Sage|CreatureCohortsTheGenie|Djinni|CreatureCohortsTheGenie|3",
				"Carry the Storm|Warrior-Sage|CreatureCohortsTheGenie|Djinni|CreatureCohortsTheGenie|7",
				"Auran Avatar|Warrior-Sage|CreatureCohortsTheGenie|Djinni|CreatureCohortsTheGenie|10",
				"From Above the Skies|Warrior-Sage|CreatureCohortsTheGenie|Djinni|CreatureCohortsTheGenie|15"
			]
		},
		{
			"name": "Efreeti",
			"shortName": "Efreeti",
			"source": "CreatureCohortsTheGenie",
			"className": "Warrior-Sage",
			"classSource": "CreatureCohortsTheGenie",
			"page": 10,
			"additionalSpells": [
				{
					"known": {
						"3": [
							"burning hands",
							"chromatic orb"
						],
						"5": [
							"enlarge/reduce",
							"scorching ray"
						],
						"9": [
							"haste",
							"protection from energy"
						],
						"13": [
							"fire shield",
							"wall of fire"
						],
						"17": [
							"conjure elemental (fire elemental only)",
							"dominate person"
						]
					}
				}
			],
			"subclassFeatures": [
				"Efreeti|Warrior-Sage|CreatureCohortsTheGenie|Efreeti|CreatureCohortsTheGenie|3",
				"Obsidian Advocate|Warrior-Sage|CreatureCohortsTheGenie|Efreeti|CreatureCohortsTheGenie|7",
				"Ignan Mastery|Warrior-Sage|CreatureCohortsTheGenie|Efreeti|CreatureCohortsTheGenie|10",
				"From Within the Flames|Warrior-Sage|CreatureCohortsTheGenie|Efreeti|CreatureCohortsTheGenie|15"
			]
		},
		{
			"name": "Marid",
			"shortName": "Marid",
			"source": "CreatureCohortsTheGenie",
			"className": "Warrior-Sage",
			"classSource": "CreatureCohortsTheGenie",
			"page": 11,
			"additionalSpells": [
				{
					"known": {
						"3": [
							"armor of agathys",
							"create or destroy water"
						],
						"5": [
							"hold person",
							"mirror image"
						],
						"9": [
							"sleet storm",
							"water walk"
						],
						"13": [
							"control water",
							"ice storm"
						],
						"17": [
							"cone of cold",
							"seeming"
						]
					}
				}
			],
			"subclassFeatures": [
				"Marid|Warrior-Sage|CreatureCohortsTheGenie|Marid|CreatureCohortsTheGenie|3",
				"Tidal Throw|Warrior-Sage|CreatureCohortsTheGenie|Marid|CreatureCohortsTheGenie|7",
				"Aquan Fury|Warrior-Sage|CreatureCohortsTheGenie|Marid|CreatureCohortsTheGenie|10",
				"From Beyond the Depths|Warrior-Sage|CreatureCohortsTheGenie|Marid|CreatureCohortsTheGenie|15"
			]
		}
	],
	"classFeature": [
		{
			"name": "Grant Desire",
			"source": "CreatureCohortsTheGenie",
			"page": 5,
			"className": "Warrior-Sage",
			"classSource": "CreatureCohortsTheGenie",
			"level": 1,
			"entries": [
				"尽管只有贵族精灵才能实现真正的愿望，但许多他们的同类（以及那些追随他们教导的人）学会了以微妙的方式改变现实。",
				"作为一个奖励动作，你可以选择以下效果之一：",
				{
					"type": "list",
					"items": [
						"你可以随意改变皮肤、眼睛和头发的颜色，并且可以将身高增加或降低最多1英尺。这种效果持续1小时。",
						"你的步行速度增加了10英尺。这个效果持续1分钟。",
						"你施放了无需材料和不消耗法术位的幻影术。以这种方式施放时，法术的持续时间缩短为一分钟。"
					]
				},
				"你可以每点熟练加值使用一次这个能力，在完成一次长休后，你可以恢复任何已经使用过的次数。"
			]
		},
		{
			"name": "Natural Armor",
			"source": "CreatureCohortsTheGenie",
			"page": 5,
			"className": "Warrior-Sage",
			"classSource": "CreatureCohortsTheGenie",
			"level": 1,
			"entries": [
				"就像神话中的精灵本身一样，你的体型和肌肉结合已经被原始元素能量强化。随着你增加体重，你的魔法防护也会使你的肌肤硬化，抵御外部威胁。",
				"当你没有穿戴任何盔甲时，你的护甲等级等于10 + 你的力量修正值 + 你的体质修正值。你可以使用盾牌并仍然获得这个好处。"
			]
		},
		{
			"name": "Resilience",
			"source": "CreatureCohortsTheGenie",
			"page": 5,
			"className": "Warrior-Sage",
			"classSource": "CreatureCohortsTheGenie",
			"level": 1,
			"entries": [
				"当你受到伤害时，你可以使用一次反应，将伤害减少一个数值，该数值等同于你的熟练加值 + 你的战士智者等级。如果触发伤害是酸性、冰冷、火焰、闪电或雷电伤害，你还会在你的下一个近战或投掷武器攻击中造成额外 {@dice d6} 同类型伤害。这个额外伤害会持续到你的下一个回合结束前。",
				"你可以使用这个特性一次，并在完成一次长休后恢复任何已用次数。",
				"在第7级时，你可以在两次长休之间使用这个特性两次。在第18级时，你可以在三次长休之间使用这个特性三次。"
			]
		},
		{
			"name": "Lore-Bearer",
			"source": "CreatureCohortsTheGenie",
			"page": 5,
			"className": "Warrior-Sage",
			"classSource": "CreatureCohortsTheGenie",
			"level": 2,
			"entries": [
				"精灵，无论其起源如何，都被认为是几乎无与伦比的讲故事者。在你的旅途中，你可能也掌握了一些独特的知识。从2级开始，你可以使用你的魅力调整值代替通常需要智力调整值的任何技能检定。"
			]
		},
		{
			"name": "Planar Weapon",
			"source": "CreatureCohortsTheGenie",
			"page": 6,
			"className": "Warrior-Sage",
			"classSource": "CreatureCohortsTheGenie",
			"level": 2,
			"entries": [
				"精灵--以及值得他们秘密的盟友--学会了借助无尽的力量，让他们的武器沐浴在原始元素能量中。一些战士-贤者召唤混乱、翻滚的力量，甚至可能看起来活生生的。其他人则让他们的刀刃散发出更加控制、微妙的光芒，每次挥动都留下幽灵般的余晖。",
				"在2级时，你可以将一个法术位作为奖励动作来使你的武器缠绕着魔法力量。在1分钟内，你对生物进行武器攻击时，第一次命中时会造成额外伤害。造成的伤害可以是酸性、冰冷、火焰或闪电伤害-你在使用这个能力时可以选择。伤害类型会保持不变，直到你下次使用这个能力。",
				"此外，你所持有的任何近战武器，如果它没有\"延长\"特性或\"投掷武器\"属性，在此持续时间内将获得\"投掷武器\"属性，射程为20/60。当此能力激活时，你投掷的任何武器在每次攻击后立即飞回你的手中。",
				"额外伤害为{@dice 1d6}，对于一级法术位；{@dice 1d8} 伤害，对于二级法术位；{@dice 1d10} 伤害，来自三级法术位；{@dice 2d6} 伤害，来自四级法术位；以及{@dice 2d8} 伤害，来自五级法术位。"
			]
		},
		{
			"name": "Spellcasting",
			"source": "CreatureCohortsTheGenie",
			"page": 6,
			"className": "Warrior-Sage",
			"classSource": "CreatureCohortsTheGenie",
			"level": 2,
			"entries": [
				"到了2级，你已经成为元素位面的活体导管。战士-贤者（Warrior-Sage）法术列表在本职业描述的末尾。",
				{
					"type": "entries",
					"name": "Preparing and Casting Spells",
					"entries": [
						"战士-贤者表格显示了你用来施放法术的法术槽数量。要施放你{@filter warrior-sage spell list|spells|class=Warrior-Sage (CC:G)}中的一项1级或更高级别的法术，你必须消耗一个等级高于或等于该法术级别的法术槽。当你完成一次长休时，你会恢复所有已消耗的法术槽。",
						"你准备了可以施放的战士贤者法术清单，可以从{@filter warrior-sage spell list|spells|class=Warrior-Sage (CC:G)}中选择。在这个过程中，选择数量等于你的魅力调整值加上你的战士贤者等级一半（向下取整），最少为一个法术。这些法术必须是你拥有法术位的等级。",
						"例如，如果你是一名5级战士贤者，你有四个1级和两个2级法术位。拥有14点魅力值，你准备的法术清单可以包括四个1级或2级法术，以任意组合。如果你准备了1级法术{@spell burning hands}，你可以使用1级或2级法术位施放它。施放该法术不会将其从你的准备法术清单中移除。",
						"你可以在完成一次长休后更改你准备的法术清单。准备一份新的战士贤者法术清单需要安静反思的时间：每个法术等级至少1分钟，每个法术在你的清单上。"
					]
				},
				{
					"type": "entries",
					"name": "Spellcasting Ability",
					"entries": [
						"魅力是你的法术施放能力，用于你的战士贤者法术，因为它们的力量来自于你通过意志力控制元素。每当一个法术提到你的法术施放能力时，你就使用你的魅力。此外，当你施放战士贤者法术并设定豁免 DC 或进行攻击检定时，你也使用你的魅力调整值。",
						{
							"type": "abilityDc",
							"name": "Spell",
							"attributes": [
								"cha"
							]
						},
						{
							"type": "abilityAttackMod",
							"name": "Spell",
							"attributes": [
								"cha"
							]
						}
					]
				},
				{
					"type": "entries",
					"name": "Spellcasting Focus",
					"entries": [
						"你可以使用由贵金属（如银、金或铂金）制成的珠宝作为你的战士贤者法术的施法焦点。这包括戒指、护身符、项链和手镯等物品，例如。"
					]
				}
			]
		},
		{
			"name": "Ageless Technique",
			"source": "CreatureCohortsTheGenie",
			"page": 6,
			"className": "Warrior-Sage",
			"classSource": "CreatureCohortsTheGenie",
			"level": 3,
			"entries": [
				"精灵和他们的同类随身携带着世代智慧-在他们坚韧的肉体和热烈的笑声背后隐藏着无数战斗技巧的知识。然而，同样重要的是，一个战士-贤者需要具备超越当下的能力，建立起执行这些技巧所需的极端专注力。",
				"从3级开始，一位战士贤者可以利用他们的移动动作停留在原地并集中精神。作为交换条件，战士贤者在接下来的回合结束前进行的下一个近战或投掷武器攻击获得优势。",
				"战士贤者可以使用这个能力的次数没有限制。如果战士贤者在这个回合中的任何移动部分已经被使用过，则无法使用这个能力。"
			]
		},
		{
			"name": "Aspect",
			"source": "CreatureCohortsTheGenie",
			"page": 7,
			"className": "Warrior-Sage",
			"classSource": "CreatureCohortsTheGenie",
			"level": 3,
			"entries": [
				"战士贤者对元素拥有巨大的力量。话虽如此，其中最强大的人往往会将他们的联系集中在一个元素方面，超越其他一切。",
				"如果你的同伴被创建为一个玩家角色（或者它被认为具有相同的能力水平），那么在3级时，你选择你的子类-- 道（Dao）, 风精（Djinni）, 火精（Efreeti）, 或 水精（Marid）。方面选项在这个职业描述的末尾有详细说明。",
				"你的选择在3级时赋予你特性，之后分别在7级、10级和15级再次获得。这些特性包括(Aspect spells)。",
				{
					"type": "entries",
					"name": "Aspect Spells",
					"entries": [
						"每个方面都有一系列相关的法术。您在方面描述中指定的级别获得对这些法术的访问权限。一旦获得对一个方面法术的访问权限，您将始终准备好该法术。方面法术不计入您每天可以准备的法术数量。",
						"如果你获得了一个不在战士-贤者法术清单上的特质法术，那么对你来说，这个法术仍然是一种战士-贤者法术。"
					]
				}
			]
		},
		{
			"name": "Aspect Feature",
			"source": "CreatureCohortsTheGenie",
			"page": 8,
			"className": "Warrior-Sage",
			"classSource": "CreatureCohortsTheGenie",
			"level": 3,
			"entries": [
				"在3级时，你获得了由你的本质（Aspect）赋予的特性。"
			]
		},
		{
			"name": "Ability Score Improvement",
			"source": "CreatureCohortsTheGenie",
			"className": "Warrior-Sage",
			"classSource": "CreatureCohortsTheGenie",
			"level": 4,
			"entries": [
				"当你达到4级时，你可以选择将一个能力值提高2点，或者将两个能力值提高1点。与正常规则一样，使用此特性不能将能力值提高到20以上。",
				"如果你的DM允许使用专长，你可以选择取得一个{@5etools feat|feats.html}。"
			]
		},
		{
			"name": "Extra Attack",
			"source": "CreatureCohortsTheGenie",
			"page": 7,
			"className": "Warrior-Sage",
			"classSource": "CreatureCohortsTheGenie",
			"level": 5,
			"entries": [
				"在5级时，当你使用攻击动作时，你可以进行两次攻击，而不是一次。"
			]
		},
		{
			"name": "Might of the Elements",
			"source": "CreatureCohortsTheGenie",
			"page": 7,
			"className": "Warrior-Sage",
			"classSource": "CreatureCohortsTheGenie",
			"level": 6,
			"entries": [
				"战士贤者不仅接受精灵的教导，随着时间的推移，他们获得了他们祖先的无上力量和轻松飞行的能力。",
				"从6级开始，你在确定携带能力和推、拉或举起重量时被视为比实际体型大一级。这与强壮体格特质不可叠加。",
				"此外，你获得60英尺的飞行速度。如果你之前已经拥有飞行速度（比如来自（精灵种族）），你在空中结束回合时不再掉落。"
			]
		},
		{
			"name": "Aspect Feature",
			"source": "CreatureCohortsTheGenie",
			"page": 8,
			"className": "Warrior-Sage",
			"classSource": "CreatureCohortsTheGenie",
			"level": 7,
			"entries": [
				"在第7级时，你获得了由你的本质（Aspect）赋予的特性。"
			]
		},
		{
			"name": "Resilience (2)",
			"source": "CreatureCohortsTheGenie",
			"page": 5,
			"className": "Warrior-Sage",
			"classSource": "CreatureCohortsTheGenie",
			"level": 7,
			"entries": [
				"从第7级开始，你可以在两次长休之间使用这个特性。"
			]
		},
		{
			"name": "Ability Score Improvement",
			"source": "CreatureCohortsTheGenie",
			"className": "Warrior-Sage",
			"classSource": "CreatureCohortsTheGenie",
			"level": 8,
			"entries": [
				"当你达到8级时，你可以选择将一个能力值提高2点，或者将两个能力值提高1点。与正常规则一样，使用此特性不能将能力值提高到20以上。",
				"如果你的DM允许使用专长，你可以选择取得一个{@5etools feat|feats.html}。"
			]
		},
		{
			"name": "Aspect Feature",
			"source": "CreatureCohortsTheGenie",
			"page": 8,
			"className": "Warrior-Sage",
			"classSource": "CreatureCohortsTheGenie",
			"level": 10,
			"entries": [
				"在10级时，你获得了由你的本质（Aspect）赋予的特性。"
			]
		},
		{
			"name": "Planar Conduit",
			"source": "CreatureCohortsTheGenie",
			"page": 7,
			"className": "Warrior-Sage",
			"classSource": "CreatureCohortsTheGenie",
			"level": 11,
			"entries": [
				"随着你与元素位面的联系增强，你手中的可能性也随之增加。只要你允许，你无拘无束的力量可以流过你手中的任何武器。",
				"从11级开始，你所有的近战和投掷武器攻击在命中时额外造成{@dice 1d8}伤害。这种伤害可以是酸性、冰冷、火焰或闪电伤害- 你可以在你的回合内无需行动改变伤害类型，但每轮只能改变一次。",
				"此外，你的位面武器伤害增加（尽管仍然只影响你在一轮中第一次命中的武器攻击。）当消耗一个一级法术位时，额外伤害现在为{@dice 1d8}，消耗二级法术位时为{@dice 1d10}，消耗三级法术位时为{@dice 2d6}，消耗四级法术位时为{@dice 2d8}，消耗五级法术位时为{@dice 2d10}。",
				"从现在开始，使用这个能力造成的任何额外伤害，或者来自你的位面武器能力的伤害，将无视伤害抗性，但不会无视免疫能力。"
			]
		},
		{
			"name": "Ability Score Improvement",
			"source": "CreatureCohortsTheGenie",
			"className": "Warrior-Sage",
			"classSource": "CreatureCohortsTheGenie",
			"level": 12,
			"entries": [
				"当你达到12级时，你可以选择将一个能力值提高2点，或者将两个能力值提高1点。与通常一样，使用此特性时不能将能力值提高到20以上。",
				"如果你的DM允许使用专长，你可以选择取得一个{@5etools feat|feats.html}。"
			]
		},
		{
			"name": "Plane Shift",
			"source": "CreatureCohortsTheGenie",
			"page": 7,
			"className": "Warrior-Sage",
			"classSource": "CreatureCohortsTheGenie",
			"level": 14,
			"entries": [
				"在14级时，你获得了无需消耗法术位即可施展位面转移法术的能力。如果你的目的地位于物质位面或元素位面之一（比如空气、土地、火焰或水元素位面），那么你在这种方式下施展法术时无需任何材料组件。",
				"如果你的目的地在你当前的存在平面上，你可以使用这个能力来施放{@spell teleport}法术。",
				"你可以使用这个能力一次，在完成一次长休后，你可以恢复任何已用次数。"
			]
		},
		{
			"name": "Aspect Feature",
			"source": "CreatureCohortsTheGenie",
			"page": 8,
			"className": "Warrior-Sage",
			"classSource": "CreatureCohortsTheGenie",
			"level": 15,
			"entries": [
				"在15级时，你获得了由你的本质（Aspect）赋予的特性。"
			]
		},
		{
			"name": "Ability Score Improvement",
			"source": "CreatureCohortsTheGenie",
			"className": "Warrior-Sage",
			"classSource": "CreatureCohortsTheGenie",
			"level": 16,
			"entries": [
				"当你达到16级时，你可以选择将一个能力值提高2点，或者将两个能力值提高1点。与正常规则一样，使用这个特性不能将能力值提高到20以上。",
				"如果你的DM允许使用专长，你可以选择取得一个{@5etools feat|feats.html}。"
			]
		},
		{
			"name": "Resilience (3)",
			"source": "CreatureCohortsTheGenie",
			"page": 5,
			"className": "Warrior-Sage",
			"classSource": "CreatureCohortsTheGenie",
			"level": 18,
			"entries": [
				"从18级开始，你可以在两次长休之间使用这个特性三次。"
			]
		},
		{
			"name": "Ability Score Improvement",
			"source": "CreatureCohortsTheGenie",
			"className": "Warrior-Sage",
			"classSource": "CreatureCohortsTheGenie",
			"level": 19,
			"entries": [
				"当你达到19级时，你可以选择将一个能力值提高2点，或者将两个能力值提高1点。与通常一样，你不能通过这个特性将一个能力值提高到20以上。",
				"如果你的DM允许使用专长，你可以选择取得一个{@5etools feat|feats.html}。"
			]
		},
		{
			"name": "Wishmonger",
			"source": "CreatureCohortsTheGenie",
			"page": 7,
			"className": "Warrior-Sage",
			"classSource": "CreatureCohortsTheGenie",
			"level": 20,
			"entries": [
				"在20级时，你可以将你的许愿能力用作一个动作，召唤一个施法时间为1个行动且等级为3或更低的法术效果。这个法术可以来自任何职业的法术列表，你不需要满足该法术的要求，包括昂贵的材料成分；这个法术只是作为这个动作的一部分生效。",
				"你可以使用这个能力两次，在完成一次长休后，所有已用次数将会恢复。",
				"作为替代，你可以施放一项6级或更低级别的单个法术，而不是上述的（相同条件仍然适用）。你必须在此方式下施放4级或更高级别的法术时拥有这项能力的两次使用机会，并且在这样做时消耗这两次使用机会。",
				"一旦你使用这个能力施放4级或更高级别的法术，你就不能以这种方式再施放另一个4级或更高级别的法术，直到你完成{@dice 1d4}个长休。"
			]
		}
	],
	"subclassFeature": [
		{
			"name": "Dao",
			"source": "CreatureCohortsTheGenie",
			"page": 8,
			"className": "Warrior-Sage",
			"classSource": "CreatureCohortsTheGenie",
			"subclassShortName": "Dao",
			"subclassSource": "CreatureCohortsTheGenie",
			"level": 3,
			"entries": [
				"道（Dao）以他们的坚韧性和残酷性而闻名。通过坚硬的肌肤和大胆的决心，道仍然屹立不倒，即使其他精灵可能会失败。他们在召唤和驱逐魔法方面也拥有相当的技巧。这对于控制那些为他们服务的人，或者那些胆大到敢于抵抗他们的力量的人来说都是更好的。",
				{
					"type": "refSubclassFeature",
					"subclassFeature": "Aspect Spells|Warrior-Sage|CreatureCohortsTheGenie|Dao|CreatureCohortsTheGenie|3"
				},
				{
					"type": "refSubclassFeature",
					"subclassFeature": "Wishmaker|Warrior-Sage|CreatureCohortsTheGenie|Dao|CreatureCohortsTheGenie|3"
				},
				{
					"type": "refSubclassFeature",
					"subclassFeature": "Belligerent Flesh|Warrior-Sage|CreatureCohortsTheGenie|Dao|CreatureCohortsTheGenie|3"
				},
				{
					"type": "refSubclassFeature",
					"subclassFeature": "Earthen Lord|Warrior-Sage|CreatureCohortsTheGenie|Dao|CreatureCohortsTheGenie|3"
				}
			]
		},
		{
			"name": "Aspect Spells",
			"source": "CreatureCohortsTheGenie",
			"page": 8,
			"className": "Warrior-Sage",
			"classSource": "CreatureCohortsTheGenie",
			"subclassShortName": "Dao",
			"subclassSource": "CreatureCohortsTheGenie",
			"level": 3,
			"header": 1,
			"entries": [
				"{@i 3rd-level Dao Feature}",
				"你在列出的战士-贤者等级上获得特质法术。",
				{
					"type": "table",
					"name": "Aspect Spells",
					"caption": "Aspect Spells",
					"colLabels": [
						"Warrior-Sage Level",
						"Spells"
					],
					"colStyles": [
						"col-2 text-center",
						"col-10"
					],
					"rows": [
						[
							"3rd",
							"{@spell compelled duel}, {@spell shield}"
						],
						[
							"5th",
							"{@spell melf's acid arrow}, {@spell ray of enfeeblement}"
						],
						[
							"9th",
							"{@spell magic circle}, {@spell meld into stone}"
						],
						[
							"13th",
							"{@spell banishment}, {@spell stone shape}"
						],
						[
							"17th",
							"{@spell hold monster}, {@spell planar binding}"
						]
					]
				}
			]
		},
		{
			"name": "Belligerent Flesh",
			"source": "CreatureCohortsTheGenie",
			"page": 8,
			"className": "Warrior-Sage",
			"classSource": "CreatureCohortsTheGenie",
			"subclassShortName": "Dao",
			"subclassSource": "CreatureCohortsTheGenie",
			"level": 3,
			"header": 1,
			"entries": [
				"{@i 3rd-level Dao Feature}",
				"在3级时，你可以使用愿望使者能力中的意志点来抵抗不良影响。每当你被迫进行豁免检定时，你可以在进行检定之前至少花费一个意志点。你在豁免检定上获得的奖励等同于以这种方式花费的意志点数量。",
				"每次使用这个能力时，您可以花费多达一个意志点来提升熟练加值的点数。"
			]
		},
		{
			"name": "Earthen Lord",
			"source": "CreatureCohortsTheGenie",
			"page": 8,
			"className": "Warrior-Sage",
			"classSource": "CreatureCohortsTheGenie",
			"subclassShortName": "Dao",
			"subclassSource": "CreatureCohortsTheGenie",
			"level": 3,
			"header": 1,
			"entries": [
				"{@i 3rd-level Dao Feature}",
				"从3级开始，当使用双手武器（或双手持握的万能武器）并站在坚实地面上时，你的AC获得+1的加值。"
			]
		},
		{
			"name": "Wishmaker",
			"source": "CreatureCohortsTheGenie",
			"page": 8,
			"className": "Warrior-Sage",
			"classSource": "CreatureCohortsTheGenie",
			"subclassShortName": "Dao",
			"subclassSource": "CreatureCohortsTheGenie",
			"level": 3,
			"header": 1,
			"entries": [
				"{@i 3rd-level Dao Feature}",
				"从3级开始，你获得了一项能力，可以保留你消耗的任何奥术能量的一小部分，用它来激发其他能力。",
				"每当你使用一个法术位施放一个战士贤者法术，或者为你的位面武器能力消耗一个法术位时，你会获得一个意志点。当你完成一次长休时，你的意志点总数重置为零。",
				"作为一个奖励动作，你可以消耗意志点来获得临时生命值。当你这样做时，每消耗一个意志点，你获得三点临时生命值。每次使用这个能力时，你可以最多消耗与熟练加值相等的意志点。",
				"每个战士-贤者子职业都提供了一种额外的方式来使用从这项能力中获得的意志点数。"
			]
		},
		{
			"name": "Appeal to Power",
			"source": "CreatureCohortsTheGenie",
			"page": 8,
			"className": "Warrior-Sage",
			"classSource": "CreatureCohortsTheGenie",
			"subclassShortName": "Dao",
			"subclassSource": "CreatureCohortsTheGenie",
			"level": 7,
			"header": 2,
			"entries": [
				"{@i 7th-level Dao Feature}",
				"从7级开始，每当你使用你的无古不可技能时，你可以选择你的近战武器射程内的任意数量生物。这些生物中的每一个必须根据你的施法豁免 DC 进行一次感知豁免，否则在1分钟内变成{@condition frightened}。",
				"在受影响目标的每个回合结束时，可以进行另一次感知豁免投掷，若成功则结束{@condition frightened}状态。",
				"你可以每点熟练加值使用一次这个能力，在完成一次长休后，你可以恢复任何已经使用过的次数。"
			]
		},
		{
			"name": "Terran Heritage",
			"source": "CreatureCohortsTheGenie",
			"page": 8,
			"className": "Warrior-Sage",
			"classSource": "CreatureCohortsTheGenie",
			"subclassShortName": "Dao",
			"subclassSource": "CreatureCohortsTheGenie",
			"level": 10,
			"header": 2,
			"entries": [
				"{@i 10th-level Dao Feature}",
				"在10级时，你获得对酸性伤害的抗性。此外，每当你对一只生物造成重击时，该生物必须根据你的施法豁免 DC 进行一次感知豁免检定。如果未通过检定，则该生物在你的下一个回合结束前变为 {@condition stunned}。"
			]
		},
		{
			"name": "From Beneath the Earth",
			"source": "CreatureCohortsTheGenie",
			"page": 8,
			"className": "Warrior-Sage",
			"classSource": "CreatureCohortsTheGenie",
			"subclassShortName": "Dao",
			"subclassSource": "CreatureCohortsTheGenie",
			"level": 15,
			"header": 2,
			"entries": [
				"{@i 15th-level Dao Feature}",
				"从15级开始，每当你使用你的坚韧能力时，你会获得一个临时生命值，数值等同于你战士贤者等级的一半，向上取整。这些临时生命值会在你从该能力减少的伤害后立即生效，但前提是你仍然清醒。"
			]
		},
		{
			"name": "Djinni",
			"source": "CreatureCohortsTheGenie",
			"page": 9,
			"className": "Warrior-Sage",
			"classSource": "CreatureCohortsTheGenie",
			"subclassShortName": "Djinni",
			"subclassSource": "CreatureCohortsTheGenie",
			"level": 3,
			"entries": [
				"在所有已知的精灵中，没有一个像(风之精灵)那样广为人知（或者在某些情况下，如此公开受欢迎）。巨灵可以勇敢，有时也很虚荣，但他们的伴侣很少会轻易放过他们。他们出色的速度和技巧使他们成为那些足够强大以困住他们的人的可怕仆人。然而，他们对生活的热爱使他们更有价值，作为朋友和同胞。",
				{
					"type": "refSubclassFeature",
					"subclassFeature": "Aspect Spells|Warrior-Sage|CreatureCohortsTheGenie|Djinni|CreatureCohortsTheGenie|3"
				},
				{
					"type": "refSubclassFeature",
					"subclassFeature": "Wishmaker|Warrior-Sage|CreatureCohortsTheGenie|Djinni|CreatureCohortsTheGenie|3"
				},
				{
					"type": "refSubclassFeature",
					"subclassFeature": "Sudden Step|Warrior-Sage|CreatureCohortsTheGenie|Djinni|CreatureCohortsTheGenie|3"
				},
				{
					"type": "refSubclassFeature",
					"subclassFeature": "Thunder Lord|Warrior-Sage|CreatureCohortsTheGenie|Djinni|CreatureCohortsTheGenie|3"
				}
			]
		},
		{
			"name": "Aspect Spells",
			"source": "CreatureCohortsTheGenie",
			"page": 9,
			"className": "Warrior-Sage",
			"classSource": "CreatureCohortsTheGenie",
			"subclassShortName": "Djinni",
			"subclassSource": "CreatureCohortsTheGenie",
			"level": 3,
			"header": 1,
			"entries": [
				"{@i 3rd-level Djinni Feature}",
				"你在列出的战士-贤者等级上获得特质法术。",
				{
					"type": "table",
					"name": "Aspect Spells",
					"caption": "Aspect Spells",
					"colLabels": [
						"Warrior-Sage Level",
						"Spells"
					],
					"colStyles": [
						"col-2 text-center",
						"col-10"
					],
					"rows": [
						[
							"3rd",
							"{@spell magic missile}, {@spell shield}"
						],
						[
							"5th",
							"{@spell misty step}, {@spell invisibility}"
						],
						[
							"9th",
							"{@spell blink}, {@spell lightning arrow}"
						],
						[
							"13th",
							"{@spell dimension door}, {@spell freedom of movement}"
						],
						[
							"17th",
							"{@spell animate objects}, {@spell creation}"
						]
					]
				}
			]
		},
		{
			"name": "Sudden Step",
			"source": "CreatureCohortsTheGenie",
			"page": 9,
			"className": "Warrior-Sage",
			"classSource": "CreatureCohortsTheGenie",
			"subclassShortName": "Djinni",
			"subclassSource": "CreatureCohortsTheGenie",
			"level": 3,
			"header": 1,
			"entries": [
				"{@i 3rd-level Djinni Feature}",
				"你可以使用愿望使者能力中的意志点来进行短距离传送并穿透你的敌人。在3级时，你可以在你的回合中作为一个动作，花费至少一个意志点。选择你能看到的距离你20英尺内的任意数量生物。这些生物必须根据你的施法豁免 DC 进行敏捷豁免检定。未能通过检定的生物会受到{@dice 1d4}每个意志点花费的力量伤害（比如当花费两个意志点时为{@dice 2d4}伤害，依此类推）。",
				"然后，你可以选择一个距离你不超过5英尺的空地，每花费一个意志点。 你作为这个动作的一部分传送到那个空地。",
				"每次使用这个能力时，您可以花费多达一个意志点来提升熟练加值的点数。"
			]
		},
		{
			"name": "Thunder Lord",
			"source": "CreatureCohortsTheGenie",
			"page": 9,
			"className": "Warrior-Sage",
			"classSource": "CreatureCohortsTheGenie",
			"subclassShortName": "Djinni",
			"subclassSource": "CreatureCohortsTheGenie",
			"level": 3,
			"header": 1,
			"entries": [
				"{@i 3rd-level Djinni Feature}",
				"在3级时，你可以选择使用你的位面武器能力造成雷霆伤害，而不是其他可用的伤害类型。当你达到11级时，你也可以选择使用位面导管能力造成雷霆伤害。"
			]
		},
		{
			"name": "Wishmaker",
			"source": "CreatureCohortsTheGenie",
			"page": 9,
			"className": "Warrior-Sage",
			"classSource": "CreatureCohortsTheGenie",
			"subclassShortName": "Djinni",
			"subclassSource": "CreatureCohortsTheGenie",
			"level": 3,
			"header": 1,
			"entries": [
				"{@i 3rd-level Djinni Feature}",
				"从3级开始，你获得了一项能力，可以保留你消耗的任何奥术能量的一小部分，用它来激发其他能力。",
				"每当你使用一个法术位施放一个战士贤者法术，或者为你的位面武器能力消耗一个法术位时，你会获得一个意志点。当你完成一次长休时，你的意志点总数重置为零。",
				"作为一个奖励动作，你可以消耗意志点来获得临时生命值。当你这样做时，每消耗一个意志点，你获得三点临时生命值。每次使用这个能力时，你可以最多消耗与熟练加值相等的意志点。",
				"每个战士-贤者子职业都提供了一种额外的方式来使用从这项能力中获得的意志点数。"
			]
		},
		{
			"name": "Carry the Storm",
			"source": "CreatureCohortsTheGenie",
			"page": 9,
			"className": "Warrior-Sage",
			"classSource": "CreatureCohortsTheGenie",
			"subclassShortName": "Djinni",
			"subclassSource": "CreatureCohortsTheGenie",
			"level": 7,
			"header": 2,
			"entries": [
				"{@i 7th-level Djinni Feature}",
				"从7级开始，每当你用近战或投掷武器攻击对生物造成闪电或雷电伤害时，你可以让那个生物进行一次以你的施法豁免 DC 为目标的感知豁免检定。未通过豁免检定的生物在1分钟内变为 {@condition deafened} 和 {@condition restrained}。在他们的每个回合结束时，该生物可以进行一次新的豁免检定，成功则结束这个效果。",
				"你可以每点熟练加值使用一次这个能力，而且在完成一次长休后，你会恢复所有已用次数。"
			]
		},
		{
			"name": "Auran Avatar",
			"source": "CreatureCohortsTheGenie",
			"page": 9,
			"className": "Warrior-Sage",
			"classSource": "CreatureCohortsTheGenie",
			"subclassShortName": "Djinni",
			"subclassSource": "CreatureCohortsTheGenie",
			"level": 10,
			"header": 2,
			"entries": [
				"{@i 10th-level Djinni Feature}",
				"在10级时，你获得对闪电伤害的抗性。此外，每当你通过法术或能力传送至少10英尺时，直到下一个回合结束，你的攻击加值和护甲等级都会增加1点。"
			]
		},
		{
			"name": "From Above the Skies",
			"source": "CreatureCohortsTheGenie",
			"page": 9,
			"className": "Warrior-Sage",
			"classSource": "CreatureCohortsTheGenie",
			"subclassShortName": "Djinni",
			"subclassSource": "CreatureCohortsTheGenie",
			"level": 15,
			"header": 2,
			"entries": [
				"{@i 15th-level Djinni Feature}",
				"从15级开始，每当你在进行攻击检定时获得优势时，你可以重新投掷其中一颗骰子一次。"
			]
		},
		{
			"name": "Efreeti",
			"source": "CreatureCohortsTheGenie",
			"page": 10,
			"className": "Warrior-Sage",
			"classSource": "CreatureCohortsTheGenie",
			"subclassShortName": "Efreeti",
			"subclassSource": "CreatureCohortsTheGenie",
			"level": 3,
			"entries": [
				"通过被燃烧的刀刃和赤红的火焰，据说伊弗利特轻易地切开他们的敌人。即使在精灵中，武装的伊弗利特以剑术和法术的高效而闻名。幸运的是，他们似乎对征服物质位面没有太多野心。",
				{
					"type": "refSubclassFeature",
					"subclassFeature": "Aspect Spells|Warrior-Sage|CreatureCohortsTheGenie|Efreeti|CreatureCohortsTheGenie|3"
				},
				{
					"type": "refSubclassFeature",
					"subclassFeature": "Wishmaker|Warrior-Sage|CreatureCohortsTheGenie|Efreeti|CreatureCohortsTheGenie|3"
				},
				{
					"type": "refSubclassFeature",
					"subclassFeature": "Ember Wall|Warrior-Sage|CreatureCohortsTheGenie|Efreeti|CreatureCohortsTheGenie|3"
				},
				{
					"type": "refSubclassFeature",
					"subclassFeature": "Hand of Brass|Warrior-Sage|CreatureCohortsTheGenie|Efreeti|CreatureCohortsTheGenie|3"
				}
			]
		},
		{
			"name": "Aspect Spells",
			"source": "CreatureCohortsTheGenie",
			"page": 10,
			"className": "Warrior-Sage",
			"classSource": "CreatureCohortsTheGenie",
			"subclassShortName": "Efreeti",
			"subclassSource": "CreatureCohortsTheGenie",
			"level": 3,
			"header": 1,
			"entries": [
				"{@i 3rd-level Efreeti Feature}",
				"你在列出的战士-贤者等级上获得特质法术。",
				{
					"type": "table",
					"name": "Aspect Spells",
					"caption": "Aspect Spells",
					"colLabels": [
						"Warrior-Sage Level",
						"Spells"
					],
					"colStyles": [
						"col-2 text-center",
						"col-10"
					],
					"rows": [
						[
							"3rd",
							"{@spell burning hands}, {@spell chromatic orb}"
						],
						[
							"5th",
							"{@spell enlarge/reduce}, {@spell scorching ray}"
						],
						[
							"9th",
							"{@spell haste}, {@spell protection from energy}"
						],
						[
							"13th",
							"{@spell fire shield}, {@spell wall of fire}"
						],
						[
							"17th",
							"{@spell conjure elemental}（火元素生物专用），{@spell dominate person}"
						]
					]
				}
			]
		},
		{
			"name": "Ember Wall",
			"source": "CreatureCohortsTheGenie",
			"page": 10,
			"className": "Warrior-Sage",
			"classSource": "CreatureCohortsTheGenie",
			"subclassShortName": "Efreeti",
			"subclassSource": "CreatureCohortsTheGenie",
			"level": 3,
			"header": 1,
			"entries": [
				"{@i 3rd-level Efreeti Feature}",
				"你可以使用愿望使者能力中的意志点数来燃烧你的敌人并阻碍他们的移动。在3级时，你可以在你的回合中作为一个动作，选择一个距离你60英尺以内、你能看到的五英尺正方形区域，并花费至少一个意志点。你可以在一个15英尺宽的立方体内创建10英尺高的火柱，或者在一个25英尺长的直线上，以目标正方形位于任一形态的中心。在该区域开始他们的回合，或在一个回合内第一次进入该区域的生物，必须根据你的施法豁免 DC 进行敏捷豁免才能，否则将受到每个以这种方式花费的意志点数为单位的{@dice 1d6}火焰伤害。",
				"火柱持续两轮。每次使用此能力时，您可以花费多达熟练加值点数的意志点数中的一个。"
			]
		},
		{
			"name": "Hand of Brass",
			"source": "CreatureCohortsTheGenie",
			"page": 10,
			"className": "Warrior-Sage",
			"classSource": "CreatureCohortsTheGenie",
			"subclassShortName": "Efreeti",
			"subclassSource": "CreatureCohortsTheGenie",
			"level": 3,
			"header": 1,
			"entries": [
				"{@i 3rd-level Efreeti Feature}",
				"在3级时，每当你使用一把双手近战武器，或者双手持握一把多用武器时，你对该武器的伤害骰获得+1的奖励。"
			]
		},
		{
			"name": "Wishmaker",
			"source": "CreatureCohortsTheGenie",
			"page": 10,
			"className": "Warrior-Sage",
			"classSource": "CreatureCohortsTheGenie",
			"subclassShortName": "Efreeti",
			"subclassSource": "CreatureCohortsTheGenie",
			"level": 3,
			"header": 1,
			"entries": [
				"{@i 3rd-level Efreeti Feature}",
				"从3级开始，你获得了一项能力，可以保留你消耗的任何奥术能量的一小部分，用它来激发其他能力。",
				"每当你使用一个法术位施放一个战士贤者法术，或者为你的位面武器能力消耗一个法术位时，你会获得一个意志点。当你完成一次长休时，你的意志点总数重置为零。",
				"作为一个奖励动作，你可以消耗意志点来获得临时生命值。当你这样做时，每消耗一个意志点，你获得三点临时生命值。每次使用这个能力时，你可以最多消耗与熟练加值相等的意志点。",
				"每个战士-贤者子职业都提供了一种额外的方式来使用从这项能力中获得的意志点数。"
			]
		},
		{
			"name": "Obsidian Advocate",
			"source": "CreatureCohortsTheGenie",
			"page": 10,
			"className": "Warrior-Sage",
			"classSource": "CreatureCohortsTheGenie",
			"subclassShortName": "Efreeti",
			"subclassSource": "CreatureCohortsTheGenie",
			"level": 7,
			"header": 2,
			"entries": [
				"{@i 7th-level Efreeti Feature}",
				"从7级开始，你可以将{@spell fire bolt} cantrip作为一个奖励动作施放。如果你还不会，你也会学会{@spell fire bolt} cantrip。",
				"你可以将{@spell fire bolt}作为一个奖励动作施放，每点熟练加值一次，每完成一次长休后，你可以恢复所有已用次数。"
			]
		},
		{
			"name": "Ignan Mastery",
			"source": "CreatureCohortsTheGenie",
			"page": 10,
			"className": "Warrior-Sage",
			"classSource": "CreatureCohortsTheGenie",
			"subclassShortName": "Efreeti",
			"subclassSource": "CreatureCohortsTheGenie",
			"level": 10,
			"header": 2,
			"entries": [
				"{@i 10th-level Efreeti Feature}",
				"在10级时，你获得对火焰伤害的抗性。此外，每当你造成火焰伤害时，你能克服对该伤害类型的抗性（但不能克服免疫）。"
			]
		},
		{
			"name": "From Within the Flames",
			"source": "CreatureCohortsTheGenie",
			"page": 10,
			"className": "Warrior-Sage",
			"classSource": "CreatureCohortsTheGenie",
			"subclassShortName": "Efreeti",
			"subclassSource": "CreatureCohortsTheGenie",
			"level": 15,
			"header": 2,
			"entries": [
				"{@i 15th-level Efreeti Feature}",
				"每当你用武器攻击对生物造成火焰伤害时，你可以强迫该生物进行一次对抗你的施法豁免 DC 的体质豁免检定。生命值低于最大值一半的生物在进行此豁免检定时具有劣势。未通过此检定的生物在每个回合开始时受到 {@dice 2d6} 火焰伤害。在每个回合结束时，该生物可以进行一次新的豁免检定，成功则结束此效果。",
				"你可以每点熟练加值使用一次这个能力，在完成一次长休后，你可以恢复任何已经使用过的次数。"
			]
		},
		{
			"name": "Marid",
			"source": "CreatureCohortsTheGenie",
			"page": 11,
			"className": "Warrior-Sage",
			"classSource": "CreatureCohortsTheGenie",
			"subclassShortName": "Marid",
			"subclassSource": "CreatureCohortsTheGenie",
			"level": 3,
			"entries": [
				"精灵可能令人惊叹，但很少有像马里德那样神秘或潜在地古怪。他们对水深的掌控力无人能及，无论是他们的珊瑚堡垒还是思维都几乎无懈可击。他们的技艺通常在于远距离控制战场，然后再接近敌人的残余部分。",
				{
					"type": "refSubclassFeature",
					"subclassFeature": "Aspect Spells|Warrior-Sage|CreatureCohortsTheGenie|Marid|CreatureCohortsTheGenie|3"
				},
				{
					"type": "refSubclassFeature",
					"subclassFeature": "Wishmaker|Warrior-Sage|CreatureCohortsTheGenie|Marid|CreatureCohortsTheGenie|3"
				},
				{
					"type": "refSubclassFeature",
					"subclassFeature": "Clutch of the Sea|Warrior-Sage|CreatureCohortsTheGenie|Marid|CreatureCohortsTheGenie|3"
				},
				{
					"type": "refSubclassFeature",
					"subclassFeature": "Lord of the Trident|Warrior-Sage|CreatureCohortsTheGenie|Marid|CreatureCohortsTheGenie|3"
				}
			]
		},
		{
			"name": "Aspect Spells",
			"source": "CreatureCohortsTheGenie",
			"page": 11,
			"className": "Warrior-Sage",
			"classSource": "CreatureCohortsTheGenie",
			"subclassShortName": "Marid",
			"subclassSource": "CreatureCohortsTheGenie",
			"level": 3,
			"header": 1,
			"entries": [
				"{@i 3rd-level Marid Feature}",
				"你在列出的战士-贤者等级上获得特质法术。",
				{
					"type": "table",
					"name": "Aspect Spells",
					"caption": "Aspect Spells",
					"colLabels": [
						"Warrior-Sage Level",
						"Spells"
					],
					"colStyles": [
						"col-2 text-center",
						"col-10"
					],
					"rows": [
						[
							"3rd",
							"{@spell armor of agathys}, {@spell create or destroy water}"
						],
						[
							"5th",
							"{@spell hold person}, {@spell mirror image}"
						],
						[
							"9th",
							"{@spell sleet storm}, {@spell water walk}"
						],
						[
							"13th",
							"{@spell control water}, {@spell ice storm}"
						],
						[
							"17th",
							"{@spell cone of cold}, {@spell seeming}"
						]
					]
				}
			]
		},
		{
			"name": "Clutch of the Sea",
			"source": "CreatureCohortsTheGenie",
			"page": 11,
			"className": "Warrior-Sage",
			"classSource": "CreatureCohortsTheGenie",
			"subclassShortName": "Marid",
			"subclassSource": "CreatureCohortsTheGenie",
			"level": 3,
			"header": 1,
			"entries": [
				"{@i 3rd-level Marid Feature}",
				"你可以使用愿望使者能力中的意志点数来阻止你的敌人。在3级时，作为你回合的一个动作，你可以选择一个在你视线范围内且距离你不超过60英尺的生物，并消耗至少一个意志点。该生物必须进行一次感知豁免检定，难度等于8加上以这种方式消耗的意志点数的两倍。如果失败，该生物遭受{@spell slow}法术的影响，但它们是唯一的目标，你无需集中精力维持这个能力。受影响的生物可以在他们的回合结束时进行一次新的感知豁免检定，成功则结束效果。",
				"每次使用这个能力时，您可以花费多达一个意志点来提升熟练加值的点数。"
			]
		},
		{
			"name": "Lord of the Trident",
			"source": "CreatureCohortsTheGenie",
			"page": 11,
			"className": "Warrior-Sage",
			"classSource": "CreatureCohortsTheGenie",
			"subclassShortName": "Marid",
			"subclassSource": "CreatureCohortsTheGenie",
			"level": 3,
			"header": 1,
			"entries": [
				"{@i 3rd-level Marid Feature}",
				"在3级时，每当你使用具有投掷属性的武器时，其射程最小增加至30/90，你获得该武器攻击投掷的攻击加值+1。"
			]
		},
		{
			"name": "Wishmaker",
			"source": "CreatureCohortsTheGenie",
			"page": 11,
			"className": "Warrior-Sage",
			"classSource": "CreatureCohortsTheGenie",
			"subclassShortName": "Marid",
			"subclassSource": "CreatureCohortsTheGenie",
			"level": 3,
			"header": 1,
			"entries": [
				"{@i 3rd-level Marid Feature}",
				"从3级开始，你获得了一项能力，可以保留你消耗的任何奥术能量的一小部分，用它来激发其他能力。",
				"每当你使用一个法术位施放一个战士贤者法术，或者为你的位面武器能力消耗一个法术位时，你会获得一个意志点。当你完成一次长休时，你的意志点总数重置为零。",
				"作为一个奖励动作，你可以消耗意志点来获得临时生命值。当你这样做时，每消耗一个意志点，你获得三点临时生命值。每次使用这个能力时，你可以最多消耗与熟练加值相等的意志点。",
				"每个战士-贤者子职业都提供了一种额外的方式来使用从这项能力中获得的意志点数。"
			]
		},
		{
			"name": "Tidal Throw",
			"source": "CreatureCohortsTheGenie",
			"page": 11,
			"className": "Warrior-Sage",
			"classSource": "CreatureCohortsTheGenie",
			"subclassShortName": "Marid",
			"subclassSource": "CreatureCohortsTheGenie",
			"level": 7,
			"header": 2,
			"entries": [
				"{@i 7th-level Marid Feature}",
				"从7级开始，你可以在你的回合中，将你的武器投掷出去，并伴随着一股水流的冲击。从你身上散发出的一条60英尺长、5英尺宽的直线中的每个生物必须根据你的施法豁免 DC 进行一次敏捷豁免。如果未通过，生物会受到相同伤害类型的{@dice 4d6}伤害，如果它是巨型或更小，它会被推开20英尺，并被击倒{@condition prone}。如果通过，生物会受到一半伤害，但既不被推开也不被击倒{@condition prone}。",
				"你可以使用这个能力两次，在完成一次长休后，所有已用次数将会恢复。"
			]
		},
		{
			"name": "Aquan Fury",
			"source": "CreatureCohortsTheGenie",
			"page": 11,
			"className": "Warrior-Sage",
			"classSource": "CreatureCohortsTheGenie",
			"subclassShortName": "Marid",
			"subclassSource": "CreatureCohortsTheGenie",
			"level": 10,
			"header": 2,
			"entries": [
				"{@i 10th-level Marid Feature}",
				"在10级时，你获得对冷伤害的抗性。此外，每当你使用你的位面武器能力对生物造成额外伤害时，你可以选择原始目标周围5英尺内的另一个生物。那个生物受到等同于你的熟练加值的伤害。所造成的伤害类型与触发的额外伤害相同。"
			]
		},
		{
			"name": "From Beyond the Depths",
			"source": "CreatureCohortsTheGenie",
			"page": 11,
			"className": "Warrior-Sage",
			"classSource": "CreatureCohortsTheGenie",
			"subclassShortName": "Marid",
			"subclassSource": "CreatureCohortsTheGenie",
			"level": 15,
			"header": 2,
			"entries": [
				"{@i 15th-level Marid Feature}",
				"从15级开始，每当你用近战或投掷武器攻击命中生物时，你可以让那个生物进行一次力量豁免检定，检定 DC 为你的施法豁免 DC。如果未通过检定，该生物会受到额外的武器伤害，就像受到了重击，并被击倒{@condition prone}。",
				"你可以每点熟练加值使用一次这个能力，在完成一次长休后，你可以恢复任何已经使用过的次数。",
				"此外，即使你不在与它们相距5英尺内，对处于{@condition prone}状态的生物进行攻击骰时，你始终具有优势。"
			]
		}
	],
	"race": [
		{
			"name": "Genie",
			"source": "CreatureCohortsTheGenie",
			"page": 2,
			"lineage": "VRGR",
			"size": [
				"M"
			],
			"speed": {
				"walk": 30,
				"fly": 30
			},
			"darkvision": 60,
			"entries": [
				{
					"type": "entries",
					"name": "Age",
					"entries": [
						"据说精灵是一个凡人灵魂（或灵魂）与元素位面的广阔能量融合的结果。考虑到这一点，精灵在经历这个过程后几乎总是成年人的形态，并且似乎无法繁殖后代。精灵既不老也不死。"
					]
				},
				{
					"type": "entries",
					"name": "Alignment",
					"entries": [
						"邪恶的(道)常常在有机会时掳掠奴隶，而其中最恶劣的精灵则沉湎于对他们不幸仆人所造成的痛苦。巨灵，或空气精灵，在凡人传说中经常被提及，而且有充分的理由。在所有的精灵中，巨灵最有可能与非精灵合作，事实上他们往往觉得凡人相当迷人。著名的黄铜城的伊弗利提可能看起来和(道)一样野蛮和邪恶，但伊弗利提通过严格的等级制度和严苛的法律来统治，他们相信这是必要的以确立真正的秩序。",
						"与其他精灵不同，马利德（Marids）倾向于混乱。向马利德许愿被认为是危险的\u2014\u2014充其量，他们会先满足自己的娱乐需求，实现愿望的目的则次要，甚至可能根本不会实现。"
					]
				},
				{
					"type": "entries",
					"name": "Size",
					"entries": [
						"精灵是高大的人形生物，虽然它们起初是中等身材，但倾向于身材较高的一端。一般来说，精灵至少有六到七英尺高，更强大的精灵可能会更高。"
					]
				},
				{
					"type": "entries",
					"name": "Speed",
					"entries": [
						"你的基础移动速度是30尺。"
					]
				},
				{
					"type": "entries",
					"name": "Darkvision",
					"entries": [
						"你可以在距离你60英尺范围内的昏暗光线中看清物体，就好像是明亮的光线一样，在黑暗中也能看到物体，就好像是昏暗的光线一样。在黑暗中你无法分辨颜色，只能看到灰色调。"
					]
				},
				{
					"type": "entries",
					"name": "Elemental Nature",
					"entries": [
						"你在法术和效果方面被视为元素生物。"
					]
				},
				{
					"type": "entries",
					"name": "Flight",
					"entries": [
						"你获得了30英尺的飞行速度。你的飞行只能在短时间内持续；如果你在空中结束回合且没有其他支撑，你会坠落。",
						"如果你携带的重量超过你的最大携带能力的三分之二，你的飞行速度将只有正常速度的一半。如果你携带的重量超过你的携带能力，你将无法飞行。"
					]
				},
				{
					"type": "entries",
					"name": "Subraces",
					"entries": [
						"在D&D的各个位面中，有四大主要的元灵亚种：地元灵 (dao)、风元灵 (djinni)、火元灵 (efreet) 和水元灵 (marids)。请选择其中一种亚种。"
					]
				}
			]
		}
	],
	"subrace": [
		{
			"name": "Dao",
			"source": "CreatureCohortsTheGenie",
			"raceName": "Genie",
			"raceSource": "CreatureCohortsTheGenie",
			"entries": [
				{
					"type": "entries",
					"name": "Sure-Footed",
					"entries": [
						"刀客在对抗可能使其摔倒的效果时，对力量和敏捷豁免 throws 有优势 {@condition prone}。"
					]
				},
				{
					"type": "entries",
					"name": "Unceasing",
					"entries": [
						"当你使用你的移动动作时，你可以选择忽略艰难地形的影响，直到你的下一个回合开始。你可以使用这个能力三次，并在完成一次长休后恢复任何已使用的次数。"
					]
				},
				{
					"type": "entries",
					"name": "Elemental Boon",
					"entries": [
						"你会施放{@spell acid splash}的战斗法术。当你达到3级时，你每天可以施放{@spell ray of sickness}法术一次。当你达到5级时，你也可以每天施放{@spell melf's acid arrow}法术一次。以这种方式施放这些法术时，你不需要任何材料。这些法术的施法能力为魅力。"
					]
				}
			]
		},
		{
			"name": "Djinni",
			"source": "CreatureCohortsTheGenie",
			"raceName": "Genie",
			"raceSource": "CreatureCohortsTheGenie",
			"entries": [
				{
					"type": "entries",
					"name": "Winds of Change",
					"entries": [
						"你可以选择重新投掷一次攻击骰，如果你失败了。如果你这么做，你必须使用新的骰子点数，而且在完成一次长休前你不能再使用这个特性。"
					]
				},
				{
					"type": "entries",
					"name": "Elemental Boon",
					"entries": [
						"你会施展{@spell minor illusion}的战斗法术。当你达到3级时，你每天可以施展{@spell thunderwave}法术一次。当你达到5级时，你还可以每天施展{@spell invisibility}法术一次。以这种方式施展这些法术时，你不需要任何材料。魅力是你施展这些法术的法术属性。"
					]
				}
			]
		},
		{
			"name": "Efreeti",
			"source": "CreatureCohortsTheGenie",
			"raceName": "Genie",
			"raceSource": "CreatureCohortsTheGenie",
			"entries": [
				{
					"type": "entries",
					"name": "Flames of Fury",
					"entries": [
						"当你用法术或戏法造成伤害时，你可以选择对单个目标造成额外伤害，数值等同于你的熟练加值。这额外伤害为火焰伤害。你可以使用这个能力两次，并在完成一次长休后恢复任何已使用的次数。"
					]
				},
				{
					"type": "entries",
					"name": "Elemental Boon",
					"entries": [
						"你会{@spell fire bolt}的战斗法术。当你达到3级时，你每天可以施放{@spell burning hands}法术一次。当你达到5级时，你还可以每天施放{@spell enlarge/reduce}法术一次。以这种方式施放这些法术时，你不需要任何材料。魅力是你施放这些法术的法术能力值。"
					]
				}
			]
		},
		{
			"name": "Marid",
			"source": "CreatureCohortsTheGenie",
			"raceName": "Genie",
			"raceSource": "CreatureCohortsTheGenie",
			"speed": {
				"walk": 30,
				"fly": 30,
				"swim": 30
			},
			"entries": [
				{
					"type": "entries",
					"name": "Lords of Coral",
					"entries": [
						"你可以呼吸空气和水。你还获得了30英尺的游泳速度。"
					]
				},
				{
					"type": "entries",
					"name": "Slippery",
					"entries": [
						"当你在受到{@condition grappled}或{@condition restrained}状态影响时失败一次能力检定时，你可以重新投掷这次检定。如果你这样做，你必须使用新的骰点结果，并且在完成一次长休前无法再次使用这个特性。"
					]
				},
				{
					"type": "entries",
					"name": "Elemental Boon",
					"entries": [
						"你会{@spell ray of frost}战斗法术。当你达到3级时，你每天可以施展{@spell unseen servant}法术一次。当你达到5级时，你也可以每天施展{@spell hold person}法术一次。以这种方式施展这些法术时，你不需要任何材料。魅力是你施展这些法术的法术属性。"
					]
				}
			]
		}
	]
}
